{
  "boxInfo": {
    "boxVMax": {
      "x": 6.4043798446655,
      "y": 8.1929168701172,
      "z": 1.3526790142059
    },
    "boxVMin": {
      "x": -5.5828166007996,
      "y": 0.0,
      "z": -1.3526790142059
    }
  },
  "meshPartName": "asset/NewFolder/g2038_door_03.mesh",
  "surface": {
    "indices": [
      204,
      202,
      205,
      202,
      204,
      203,
      204,
      206,
      208,
      206,
      204,
      207,
      171,
      169,
      172,
      169,
      171,
      170,
      68,
      70,
      69,
      193,
      191,
      194,
      191,
      193,
      192,
      112,
      110,
      32,
      34,
      32,
      35,
      32,
      34,
      33,
      110,
      112,
      111,
      22,
      20,
      23,
      20,
      22,
      21,
      182,
      180,
      183,
      180,
      182,
      181,
      46,
      44,
      47,
      44,
      46,
      45,
      47,
      81,
      78,
      81,
      47,
      82,
      79,
      78,
      80,
      78,
      79,
      65,
      66,
      65,
      67,
      65,
      66,
      58,
      57,
      55,
      58,
      55,
      57,
      56,
      139,
      137,
      140,
      137,
      139,
      138,
      195,
      139,
      196,
      159,
      139,
      160,
      139,
      159,
      158,
      240,
      151,
      158,
      151,
      240,
      239,
      150,
      148,
      151,
      148,
      150,
      149,
      217,
      215,
      218,
      215,
      217,
      216,
      90,
      88,
      91,
      88,
      90,
      89,
      241,
      243,
      242,
      113,
      115,
      114,
      251,
      177,
      178,
      250,
      179,
      177,
      177,
      179,
      178,
      179,
      188,
      189,
      188,
      190,
      189,
      156,
      154,
      157,
      154,
      156,
      155,
      155,
      236,
      238,
      236,
      155,
      237,
      30,
      28,
      31,
      28,
      30,
      29,
      107,
      108,
      31,
      108,
      107,
      109,
      134,
      132,
      135,
      132,
      134,
      133,
      136,
      133,
      134,
      230,
      231,
      145,
      145,
      147,
      146,
      17,
      19,
      18,
      18,
      102,
      101,
      227,
      229,
      228,
      98,
      100,
      99,
      42,
      40,
      43,
      40,
      42,
      41,
      167,
      165,
      168,
      165,
      167,
      166,
      73,
      71,
      74,
      71,
      73,
      72,
      75,
      76,
      72,
      76,
      75,
      77,
      2,
      0,
      3,
      0,
      2,
      1,
      6,
      4,
      7,
      4,
      6,
      5,
      8,
      6,
      7,
      11,
      9,
      12,
      9,
      11,
      10,
      15,
      13,
      16,
      13,
      15,
      14,
      153,
      15,
      235,
      15,
      153,
      25,
      25,
      106,
      15,
      153,
      24,
      25,
      24,
      153,
      152,
      106,
      25,
      26,
      24,
      26,
      25,
      24,
      197,
      129,
      197,
      24,
      198,
      26,
      24,
      27,
      128,
      130,
      129,
      130,
      128,
      131,
      201,
      199,
      197,
      199,
      201,
      200,
      93,
      16,
      94,
      16,
      93,
      92,
      38,
      36,
      39,
      36,
      38,
      37,
      211,
      209,
      39,
      39,
      83,
      84,
      83,
      39,
      60,
      212,
      213,
      211,
      209,
      211,
      210,
      213,
      212,
      214,
      59,
      61,
      60,
      61,
      59,
      62,
      63,
      62,
      54,
      63,
      64,
      62,
      53,
      54,
      126,
      52,
      54,
      53,
      52,
      53,
      127,
      86,
      84,
      87,
      84,
      86,
      85,
      121,
      119,
      122,
      119,
      121,
      120,
      249,
      247,
      121,
      247,
      120,
      121,
      121,
      122,
      125,
      120,
      247,
      246,
      116,
      118,
      117,
      118,
      123,
      117,
      244,
      124,
      118,
      244,
      118,
      245,
      123,
      118,
      124,
      124,
      244,
      248,
      105,
      103,
      48,
      50,
      48,
      51,
      48,
      50,
      49,
      103,
      105,
      104,
      96,
      51,
      97,
      51,
      96,
      95,
      184,
      232,
      234,
      232,
      184,
      233,
      186,
      184,
      187,
      184,
      186,
      185,
      143,
      141,
      144,
      141,
      143,
      142,
      175,
      173,
      176,
      173,
      175,
      174,
      225,
      223,
      226,
      223,
      225,
      224,
      221,
      219,
      222,
      219,
      221,
      220,
      163,
      161,
      164,
      161,
      163,
      162
    ],
    "vertices": [
      {
        "x": -5.0309629440308,
        "y": -2.0340704917908,
        "z": -1.032231926918
      },
      {
        "x": -5.41907787323,
        "y": -4.0964574813843,
        "z": -1.1618059873581
      },
      {
        "x": -5.993597984314,
        "y": -4.0964574813843,
        "z": 0.0
      },
      {
        "x": -5.5720081329346,
        "y": -2.0206685066223,
        "z": 0.0
      },
      {
        "x": -3.7145214080811,
        "y": -2.0643084049225,
        "z": -1.1103399991989
      },
      {
        "x": -3.6141064167023,
        "y": -4.0964584350586,
        "z": -1.3087440729141
      },
      {
        "x": -4.1634140014648,
        "y": -4.0964584350586,
        "z": -1.3494939804077
      },
      {
        "x": -5.0309629440308,
        "y": -2.0340704917908,
        "z": -1.032231926918
      },
      {
        "x": -5.41907787323,
        "y": -4.0964574813843,
        "z": -1.1618059873581
      },
      {
        "x": -3.7145214080811,
        "y": -2.0643084049225,
        "z": -1.1103399991989
      },
      {
        "x": -2.9165966510773,
        "y": -1.1656775474548,
        "z": 0.0
      },
      {
        "x": -2.6806745529175,
        "y": -4.0964584350586,
        "z": 0.0
      },
      {
        "x": -3.6141064167023,
        "y": -4.0964584350586,
        "z": -1.3087440729141
      },
      {
        "x": -1.49165558815,
        "y": 3.2967257499695,
        "z": -0.89827698469162
      },
      {
        "x": -2.8597176074982,
        "y": 2.1267981529236,
        "z": -0.88494300842285
      },
      {
        "x": -3.253598690033,
        "y": 2.566906452179,
        "z": 0.0
      },
      {
        "x": -1.5032086372375,
        "y": 3.7813501358032,
        "z": 0.0
      },
      {
        "x": -2.8597176074982,
        "y": 2.1267981529236,
        "z": -0.88494300842285
      },
      {
        "x": -1.49165558815,
        "y": 3.2967257499695,
        "z": -0.89827698469162
      },
      {
        "x": -2.3501765727997,
        "y": 1.3675198554993,
        "z": -0.94353896379471
      },
      {
        "x": -0.42613762617111,
        "y": 2.1405420303345,
        "z": -0.97042095661163
      },
      {
        "x": -0.40754461288452,
        "y": 1.6180148124695,
        "z": 0.0
      },
      {
        "x": -1.9034085273743,
        "y": 0.9274115562439,
        "z": 0.0
      },
      {
        "x": -2.3501765727997,
        "y": 1.3675198554993,
        "z": -0.94353896379471
      },
      {
        "x": -4.8839797973633,
        "y": -0.26518654823303,
        "z": 0.0
      },
      {
        "x": -4.0817537307739,
        "y": 1.1283392906189,
        "z": 0.0
      },
      {
        "x": -3.8700494766235,
        "y": 0.82077932357788,
        "z": -0.88647300004959
      },
      {
        "x": -4.4849901199341,
        "y": -0.43151640892029,
        "z": -0.86584198474884
      },
      {
        "x": -3.0930914878845,
        "y": 0.12305116653442,
        "z": -0.90830099582672
      },
      {
        "x": -3.4911236763,
        "y": -0.90269041061401,
        "z": -0.9443399310112
      },
      {
        "x": -4.4849901199341,
        "y": -0.43151640892029,
        "z": -0.86584198474884
      },
      {
        "x": -3.8700494766235,
        "y": 0.82077932357788,
        "z": -0.88647300004959
      },
      {
        "x": -2.5554695129395,
        "y": -0.13229560852051,
        "z": 0.0
      },
      {
        "x": -2.9165966510773,
        "y": -1.1656775474548,
        "z": 0.0
      },
      {
        "x": -3.4911236763,
        "y": -0.90269041061401,
        "z": -0.9443399310112
      },
      {
        "x": -3.0930914878845,
        "y": 0.12305116653442,
        "z": -0.90830099582672
      },
      {
        "x": 5.993597984314,
        "y": -4.0964584350586,
        "z": 0.0
      },
      {
        "x": 5.5262298583984,
        "y": -4.0964584350586,
        "z": -1.0733909606934
      },
      {
        "x": 5.0798673629761,
        "y": -1.9748055934906,
        "z": -1.0017559528351
      },
      {
        "x": 5.4387884140015,
        "y": -1.8503565788269,
        "z": 0.0
      },
      {
        "x": 4.0440816879272,
        "y": -2.0408403873444,
        "z": -1.1440099477768
      },
      {
        "x": 5.0798673629761,
        "y": -1.9748055934906,
        "z": -1.0017559528351
      },
      {
        "x": 5.5262298583984,
        "y": -4.0964584350586,
        "z": -1.0733909606934
      },
      {
        "x": 4.5854835510254,
        "y": -4.0964584350586,
        "z": -1.3526790142059
      },
      {
        "x": 3.1908152103424,
        "y": -2.6996593475342,
        "z": -0.99403297901154
      },
      {
        "x": 3.0791063308716,
        "y": -4.0964584350586,
        "z": -0.99403297901154
      },
      {
        "x": 2.504584312439,
        "y": -4.0964584350586,
        "z": 0.0
      },
      {
        "x": 2.6419472694397,
        "y": -2.7546725273132,
        "z": 0.0
      },
      {
        "x": 2.8241791725159,
        "y": 2.8130559921265,
        "z": 0.0
      },
      {
        "x": 2.4952733516693,
        "y": 2.4599313735962,
        "z": -0.96098798513412
      },
      {
        "x": 1.4298583269119,
        "y": 3.3729228973389,
        "z": -0.67623001337051
      },
      {
        "x": 1.626796245575,
        "y": 3.6577215194702,
        "z": 0.0
      },
      {
        "x": -0.42613762617111,
        "y": 2.1405420303345,
        "z": -0.97042095661163
      },
      {
        "x": 1.4298583269119,
        "y": 3.3729228973389,
        "z": -0.67623001337051
      },
      {
        "x": 2.2484321594238,
        "y": 1.1627345085144,
        "z": -0.96098798513412
      },
      {
        "x": -0.40754461288452,
        "y": 1.6180148124695,
        "z": 0.0
      },
      {
        "x": -0.42613762617111,
        "y": 2.1405420303345,
        "z": -0.97042095661163
      },
      {
        "x": 2.2484321594238,
        "y": 1.1627345085144,
        "z": -0.96098798513412
      },
      {
        "x": 1.9034123420715,
        "y": 0.98137855529785,
        "z": 0.0
      },
      {
        "x": 4.2439155578613,
        "y": 1.2110681533813,
        "z": 0.0
      },
      {
        "x": 4.883978843689,
        "y": 0.065279483795166,
        "z": 0.0
      },
      {
        "x": 4.4120740890503,
        "y": -0.15477466583252,
        "z": -0.9551830291748
      },
      {
        "x": 3.8059322834015,
        "y": 0.86548757553101,
        "z": -0.91702598333359
      },
      {
        "x": 3.5854053497314,
        "y": -0.59488034248352,
        "z": -0.9551830291748
      },
      {
        "x": 4.4120740890503,
        "y": -0.15477466583252,
        "z": -0.9551830291748
      },
      {
        "x": 3.113495349884,
        "y": -0.81493449211121,
        "z": 0.0
      },
      {
        "x": 2.2484321594238,
        "y": 1.1627345085144,
        "z": -0.96098798513412
      },
      {
        "x": 3.5854053497314,
        "y": -0.59488034248352,
        "z": -0.9551830291748
      },
      {
        "x": -3.7145214080811,
        "y": -2.0643084049225,
        "z": -1.1103399991989
      },
      {
        "x": -3.4911236763,
        "y": -0.90269041061401,
        "z": -0.9443399310112
      },
      {
        "x": -2.9165966510773,
        "y": -1.1656775474548,
        "z": 0.0
      },
      {
        "x": -4.4849901199341,
        "y": -0.43151640892029,
        "z": -0.86584198474884
      },
      {
        "x": -5.0309629440308,
        "y": -2.0340704917908,
        "z": -1.032231926918
      },
      {
        "x": -5.5720081329346,
        "y": -2.0206685066223,
        "z": 0.0
      },
      {
        "x": -4.8839797973633,
        "y": -0.26518654823303,
        "z": 0.0
      },
      {
        "x": -3.7145214080811,
        "y": -2.0643084049225,
        "z": -1.1103399991989
      },
      {
        "x": -4.4849901199341,
        "y": -0.43151640892029,
        "z": -0.86584198474884
      },
      {
        "x": -3.4911236763,
        "y": -0.90269041061401,
        "z": -0.9443399310112
      },
      {
        "x": 3.1454784870148,
        "y": -1.8827784061432,
        "z": 0.0
      },
      {
        "x": 3.5854053497314,
        "y": -0.59488034248352,
        "z": -0.9551830291748
      },
      {
        "x": 4.0440816879272,
        "y": -2.0408403873444,
        "z": -1.1440099477768
      },
      {
        "x": 4.0440816879272,
        "y": -2.0408403873444,
        "z": -1.1440099477768
      },
      {
        "x": 3.1908152103424,
        "y": -2.6996593475342,
        "z": -0.99403297901154
      },
      {
        "x": 4.4120740890503,
        "y": -0.15477466583252,
        "z": -0.9551830291748
      },
      {
        "x": 5.0798673629761,
        "y": -1.9748055934906,
        "z": -1.0017559528351
      },
      {
        "x": 4.0440816879272,
        "y": -2.0408403873444,
        "z": -1.1440099477768
      },
      {
        "x": 3.5854053497314,
        "y": -0.59488034248352,
        "z": -0.9551830291748
      },
      {
        "x": 4.4120740890503,
        "y": -0.15477466583252,
        "z": -0.9551830291748
      },
      {
        "x": 4.5854835510254,
        "y": -4.0964584350586,
        "z": -1.3526790142059
      },
      {
        "x": 3.0791063308716,
        "y": -4.0964584350586,
        "z": -0.99403297901154
      },
      {
        "x": 3.1908152103424,
        "y": -2.6996593475342,
        "z": -0.99403297901154
      },
      {
        "x": 4.0440816879272,
        "y": -2.0408403873444,
        "z": -1.1440099477768
      },
      {
        "x": -6.556510925293e-07,
        "y": 4.0964584350586,
        "z": 0.0
      },
      {
        "x": 0.00017035007476807,
        "y": 3.5836615562439,
        "z": -0.81515097618103
      },
      {
        "x": -1.49165558815,
        "y": 3.2967257499695,
        "z": -0.89827698469162
      },
      {
        "x": 1.4298583269119,
        "y": 3.3729228973389,
        "z": -0.67623001337051
      },
      {
        "x": 0.00017035007476807,
        "y": 3.5836615562439,
        "z": -0.81515097618103
      },
      {
        "x": -6.556510925293e-07,
        "y": 4.0964584350586,
        "z": 0.0
      },
      {
        "x": -0.42613762617111,
        "y": 2.1405420303345,
        "z": -0.97042095661163
      },
      {
        "x": -1.49165558815,
        "y": 3.2967257499695,
        "z": -0.89827698469162
      },
      {
        "x": 0.00017035007476807,
        "y": 3.5836615562439,
        "z": -0.81515097618103
      },
      {
        "x": -0.42613762617111,
        "y": 2.1405420303345,
        "z": -0.97042095661163
      },
      {
        "x": -2.3501765727997,
        "y": 1.3675198554993,
        "z": -0.94353896379471
      },
      {
        "x": 4.2439155578613,
        "y": 1.2110681533813,
        "z": 0.0
      },
      {
        "x": 3.8059322834015,
        "y": 0.86548757553101,
        "z": -0.91702598333359
      },
      {
        "x": 2.4952733516693,
        "y": 2.4599313735962,
        "z": -0.96098798513412
      },
      {
        "x": -2.8597176074982,
        "y": 2.1267981529236,
        "z": -0.88494300842285
      },
      {
        "x": -3.0930914878845,
        "y": 0.12305116653442,
        "z": -0.90830099582672
      },
      {
        "x": -2.8597176074982,
        "y": 2.1267981529236,
        "z": -0.88494300842285
      },
      {
        "x": -2.3501765727997,
        "y": 1.3675198554993,
        "z": -0.94353896379471
      },
      {
        "x": -3.0930914878845,
        "y": 0.12305116653442,
        "z": -0.90830099582672
      },
      {
        "x": -2.3501765727997,
        "y": 1.3675198554993,
        "z": -0.94353896379471
      },
      {
        "x": -1.9034085273743,
        "y": 0.9274115562439,
        "z": 0.0
      },
      {
        "x": 2.2484321594238,
        "y": 1.1627345085144,
        "z": -0.96098798513412
      },
      {
        "x": 2.4952733516693,
        "y": 2.4599313735962,
        "z": -0.96098798513412
      },
      {
        "x": 3.8059322834015,
        "y": 0.86548757553101,
        "z": -0.91702598333359
      },
      {
        "x": -5.41907787323,
        "y": -4.0964574813843,
        "z": -1.1618059873581
      },
      {
        "x": -4.1634140014648,
        "y": -4.0964584350586,
        "z": -1.3494939804077
      },
      {
        "x": -5.993597984314,
        "y": -4.0964574813843,
        "z": 0.0
      },
      {
        "x": 5.5262298583984,
        "y": -4.0964584350586,
        "z": -1.0733909606934
      },
      {
        "x": 5.993597984314,
        "y": -4.0964584350586,
        "z": 0.0
      },
      {
        "x": 2.504584312439,
        "y": -4.0964584350586,
        "z": 0.0
      },
      {
        "x": 4.5854835510254,
        "y": -4.0964584350586,
        "z": -1.3526790142059
      },
      {
        "x": -3.6141064167023,
        "y": -4.0964584350586,
        "z": -1.3087440729141
      },
      {
        "x": -2.6806745529175,
        "y": -4.0964584350586,
        "z": 0.0
      },
      {
        "x": 3.0791063308716,
        "y": -4.0964584350586,
        "z": -0.99403297901154
      },
      {
        "x": 2.4952733516693,
        "y": 2.4599313735962,
        "z": -0.96098798513412
      },
      {
        "x": 0.00017035007476807,
        "y": 3.5836615562439,
        "z": -0.81515097618103
      },
      {
        "x": -5.0309629440308,
        "y": -2.0340704917908,
        "z": 1.032231926918
      },
      {
        "x": -5.5720081329346,
        "y": -2.0206685066223,
        "z": 0.0
      },
      {
        "x": -5.993597984314,
        "y": -4.0964574813843,
        "z": 0.0
      },
      {
        "x": -5.41907787323,
        "y": -4.0964574813843,
        "z": 1.1618059873581
      },
      {
        "x": -5.41907787323,
        "y": -4.0964574813843,
        "z": 1.1618059873581
      },
      {
        "x": -4.1634140014648,
        "y": -4.0964584350586,
        "z": 1.3494939804077
      },
      {
        "x": -3.7145214080811,
        "y": -2.0643084049225,
        "z": 1.1103399991989
      },
      {
        "x": -5.0309629440308,
        "y": -2.0340704917908,
        "z": 1.032231926918
      },
      {
        "x": -3.6141064167023,
        "y": -4.0964584350586,
        "z": 1.3087440729141
      },
      {
        "x": -3.6141064167023,
        "y": -4.0964584350586,
        "z": 1.3087440729141
      },
      {
        "x": -2.6806745529175,
        "y": -4.0964584350586,
        "z": 0.0
      },
      {
        "x": -2.9165966510773,
        "y": -1.1656775474548,
        "z": 0.0
      },
      {
        "x": -3.7145214080811,
        "y": -2.0643084049225,
        "z": 1.1103399991989
      },
      {
        "x": -1.5032086372375,
        "y": 3.7813501358032,
        "z": 0.0
      },
      {
        "x": -3.253598690033,
        "y": 2.566906452179,
        "z": 0.0
      },
      {
        "x": -2.8597176074982,
        "y": 2.1267981529236,
        "z": 0.88494300842285
      },
      {
        "x": -1.49165558815,
        "y": 3.2967257499695,
        "z": 0.89827698469162
      },
      {
        "x": -1.49165558815,
        "y": 3.2967257499695,
        "z": 0.89827698469162
      },
      {
        "x": -2.8597176074982,
        "y": 2.1267981529236,
        "z": 0.88494300842285
      },
      {
        "x": -2.3501765727997,
        "y": 1.3675198554993,
        "z": 0.94353896379471
      },
      {
        "x": -0.40754461288452,
        "y": 1.6180148124695,
        "z": 0.0
      },
      {
        "x": -0.42613762617111,
        "y": 2.1405420303345,
        "z": 0.97042095661163
      },
      {
        "x": -2.3501765727997,
        "y": 1.3675198554993,
        "z": 0.94353896379471
      },
      {
        "x": -1.9034085273743,
        "y": 0.9274115562439,
        "z": 0.0
      },
      {
        "x": -4.4849901199341,
        "y": -0.43151640892029,
        "z": 0.86584198474884
      },
      {
        "x": -3.8700494766235,
        "y": 0.82077932357788,
        "z": 0.88647300004959
      },
      {
        "x": -3.0930914878845,
        "y": 0.12305116653442,
        "z": 0.90830099582672
      },
      {
        "x": -3.8700494766235,
        "y": 0.82077932357788,
        "z": 0.88647300004959
      },
      {
        "x": -4.4849901199341,
        "y": -0.43151640892029,
        "z": 0.86584198474884
      },
      {
        "x": -3.4911236763,
        "y": -0.90269041061401,
        "z": 0.9443399310112
      },
      {
        "x": -2.5554695129395,
        "y": -0.13229560852051,
        "z": 0.0
      },
      {
        "x": -3.0930914878845,
        "y": 0.12305116653442,
        "z": 0.90830099582672
      },
      {
        "x": -3.4911236763,
        "y": -0.90269041061401,
        "z": 0.9443399310112
      },
      {
        "x": 5.993597984314,
        "y": -4.0964584350586,
        "z": 0.0
      },
      {
        "x": 5.4387884140015,
        "y": -1.8503565788269,
        "z": 0.0
      },
      {
        "x": 5.0798673629761,
        "y": -1.9748055934906,
        "z": 1.0017559528351
      },
      {
        "x": 5.5262298583984,
        "y": -4.0964584350586,
        "z": 1.0733909606934
      },
      {
        "x": 4.5854835510254,
        "y": -4.0964584350586,
        "z": 1.3526790142059
      },
      {
        "x": 5.5262298583984,
        "y": -4.0964584350586,
        "z": 1.0733909606934
      },
      {
        "x": 5.0798673629761,
        "y": -1.9748055934906,
        "z": 1.0017559528351
      },
      {
        "x": 4.0440816879272,
        "y": -2.0408403873444,
        "z": 1.1440099477768
      },
      {
        "x": 2.6419472694397,
        "y": -2.7546725273132,
        "z": 0.0
      },
      {
        "x": 2.504584312439,
        "y": -4.0964584350586,
        "z": 0.0
      },
      {
        "x": 3.0791063308716,
        "y": -4.0964584350586,
        "z": 0.99403297901154
      },
      {
        "x": 3.1908152103424,
        "y": -2.6996593475342,
        "z": 0.99403297901154
      },
      {
        "x": 2.8241791725159,
        "y": 2.8130559921265,
        "z": 0.0
      },
      {
        "x": 1.626796245575,
        "y": 3.6577215194702,
        "z": 0.0
      },
      {
        "x": 1.4298583269119,
        "y": 3.3729228973389,
        "z": 0.67623001337051
      },
      {
        "x": 2.4952733516693,
        "y": 2.4599313735962,
        "z": 0.96098798513412
      },
      {
        "x": 1.4298583269119,
        "y": 3.3729228973389,
        "z": 0.67623001337051
      },
      {
        "x": -0.42613762617111,
        "y": 2.1405420303345,
        "z": 0.97042095661163
      },
      {
        "x": 2.2484321594238,
        "y": 1.1627345085144,
        "z": 0.96098798513412
      },
      {
        "x": -0.40754461288452,
        "y": 1.6180148124695,
        "z": 0.0
      },
      {
        "x": 1.9034123420715,
        "y": 0.98137855529785,
        "z": 0.0
      },
      {
        "x": 2.2484321594238,
        "y": 1.1627345085144,
        "z": 0.96098798513412
      },
      {
        "x": -0.42613762617111,
        "y": 2.1405420303345,
        "z": 0.97042095661163
      },
      {
        "x": 4.2439155578613,
        "y": 1.2110681533813,
        "z": 0.0
      },
      {
        "x": 3.8059322834015,
        "y": 0.86548757553101,
        "z": 0.91702598333359
      },
      {
        "x": 4.4120740890503,
        "y": -0.15477466583252,
        "z": 0.9551830291748
      },
      {
        "x": 4.883978843689,
        "y": 0.065279483795166,
        "z": 0.0
      },
      {
        "x": 3.8059322834015,
        "y": 0.86548757553101,
        "z": 0.91702598333359
      },
      {
        "x": 3.5854053497314,
        "y": -0.59488034248352,
        "z": 0.9551830291748
      },
      {
        "x": 4.4120740890503,
        "y": -0.15477466583252,
        "z": 0.9551830291748
      },
      {
        "x": 3.5854053497314,
        "y": -0.59488034248352,
        "z": 0.9551830291748
      },
      {
        "x": 2.2484321594238,
        "y": 1.1627345085144,
        "z": 0.96098798513412
      },
      {
        "x": 1.9034123420715,
        "y": 0.98137855529785,
        "z": 0.0
      },
      {
        "x": 3.113495349884,
        "y": -0.81493449211121,
        "z": 0.0
      },
      {
        "x": -3.4911236763,
        "y": -0.90269041061401,
        "z": 0.9443399310112
      },
      {
        "x": -3.7145214080811,
        "y": -2.0643084049225,
        "z": 1.1103399991989
      },
      {
        "x": -5.0309629440308,
        "y": -2.0340704917908,
        "z": 1.032231926918
      },
      {
        "x": -4.4849901199341,
        "y": -0.43151640892029,
        "z": 0.86584198474884
      },
      {
        "x": -3.7145214080811,
        "y": -2.0643084049225,
        "z": 1.1103399991989
      },
      {
        "x": -3.4911236763,
        "y": -0.90269041061401,
        "z": 0.9443399310112
      },
      {
        "x": -4.4849901199341,
        "y": -0.43151640892029,
        "z": 0.86584198474884
      },
      {
        "x": 3.5854053497314,
        "y": -0.59488034248352,
        "z": 0.9551830291748
      },
      {
        "x": 3.113495349884,
        "y": -0.81493449211121,
        "z": 0.0
      },
      {
        "x": 3.1454784870148,
        "y": -1.8827784061432,
        "z": 0.0
      },
      {
        "x": 4.0440816879272,
        "y": -2.0408403873444,
        "z": 1.1440099477768
      },
      {
        "x": 3.1908152103424,
        "y": -2.6996593475342,
        "z": 0.99403297901154
      },
      {
        "x": 4.0440816879272,
        "y": -2.0408403873444,
        "z": 1.1440099477768
      },
      {
        "x": 2.6419472694397,
        "y": -2.7546725273132,
        "z": 0.0
      },
      {
        "x": 4.883978843689,
        "y": 0.065279483795166,
        "z": 0.0
      },
      {
        "x": 4.4120740890503,
        "y": -0.15477466583252,
        "z": 0.9551830291748
      },
      {
        "x": 5.0798673629761,
        "y": -1.9748055934906,
        "z": 1.0017559528351
      },
      {
        "x": 4.0440816879272,
        "y": -2.0408403873444,
        "z": 1.1440099477768
      },
      {
        "x": 4.4120740890503,
        "y": -0.15477466583252,
        "z": 0.9551830291748
      },
      {
        "x": 3.5854053497314,
        "y": -0.59488034248352,
        "z": 0.9551830291748
      },
      {
        "x": 4.5854835510254,
        "y": -4.0964584350586,
        "z": 1.3526790142059
      },
      {
        "x": 4.0440816879272,
        "y": -2.0408403873444,
        "z": 1.1440099477768
      },
      {
        "x": 3.1908152103424,
        "y": -2.6996593475342,
        "z": 0.99403297901154
      },
      {
        "x": 3.0791063308716,
        "y": -4.0964584350586,
        "z": 0.99403297901154
      },
      {
        "x": 0.00017035007476807,
        "y": 3.5836615562439,
        "z": 0.81515097618103
      },
      {
        "x": -6.556510925293e-07,
        "y": 4.0964584350586,
        "z": 0.0
      },
      {
        "x": -1.5032086372375,
        "y": 3.7813501358032,
        "z": 0.0
      },
      {
        "x": -1.49165558815,
        "y": 3.2967257499695,
        "z": 0.89827698469162
      },
      {
        "x": 1.626796245575,
        "y": 3.6577215194702,
        "z": 0.0
      },
      {
        "x": -6.556510925293e-07,
        "y": 4.0964584350586,
        "z": 0.0
      },
      {
        "x": 0.00017035007476807,
        "y": 3.5836615562439,
        "z": 0.81515097618103
      },
      {
        "x": 1.4298583269119,
        "y": 3.3729228973389,
        "z": 0.67623001337051
      },
      {
        "x": -1.49165558815,
        "y": 3.2967257499695,
        "z": 0.89827698469162
      },
      {
        "x": -0.42613762617111,
        "y": 2.1405420303345,
        "z": 0.97042095661163
      },
      {
        "x": 0.00017035007476807,
        "y": 3.5836615562439,
        "z": 0.81515097618103
      },
      {
        "x": -0.42613762617111,
        "y": 2.1405420303345,
        "z": 0.97042095661163
      },
      {
        "x": -2.3501765727997,
        "y": 1.3675198554993,
        "z": 0.94353896379471
      },
      {
        "x": 2.4952733516693,
        "y": 2.4599313735962,
        "z": 0.96098798513412
      },
      {
        "x": 3.8059322834015,
        "y": 0.86548757553101,
        "z": 0.91702598333359
      },
      {
        "x": 2.8241791725159,
        "y": 2.8130559921265,
        "z": 0.0
      },
      {
        "x": -2.8597176074982,
        "y": 2.1267981529236,
        "z": 0.88494300842285
      },
      {
        "x": -2.3501765727997,
        "y": 1.3675198554993,
        "z": 0.94353896379471
      },
      {
        "x": -2.8597176074982,
        "y": 2.1267981529236,
        "z": 0.88494300842285
      },
      {
        "x": -3.0930914878845,
        "y": 0.12305116653442,
        "z": 0.90830099582672
      },
      {
        "x": -2.3501765727997,
        "y": 1.3675198554993,
        "z": 0.94353896379471
      },
      {
        "x": -3.0930914878845,
        "y": 0.12305116653442,
        "z": 0.90830099582672
      },
      {
        "x": 2.4952733516693,
        "y": 2.4599313735962,
        "z": 0.96098798513412
      },
      {
        "x": 2.2484321594238,
        "y": 1.1627345085144,
        "z": 0.96098798513412
      },
      {
        "x": 3.8059322834015,
        "y": 0.86548757553101,
        "z": 0.91702598333359
      },
      {
        "x": -4.1634140014648,
        "y": -4.0964584350586,
        "z": 1.3494939804077
      },
      {
        "x": -5.41907787323,
        "y": -4.0964574813843,
        "z": 1.1618059873581
      },
      {
        "x": 5.5262298583984,
        "y": -4.0964584350586,
        "z": 1.0733909606934
      },
      {
        "x": 4.5854835510254,
        "y": -4.0964584350586,
        "z": 1.3526790142059
      },
      {
        "x": -3.6141064167023,
        "y": -4.0964584350586,
        "z": 1.3087440729141
      },
      {
        "x": 3.0791063308716,
        "y": -4.0964584350586,
        "z": 0.99403297901154
      },
      {
        "x": 2.4952733516693,
        "y": 2.4599313735962,
        "z": 0.96098798513412
      },
      {
        "x": 0.00017035007476807,
        "y": 3.5836615562439,
        "z": 0.81515097618103
      }
    ]
  }
}