{
  "data": {
    "triggers": {
      "list": [
        {
          "actions": [
            {
              "__OBJ_TYPE": "Action_GetPartPosition",
              "components": [
                {
                  "__OBJ_TYPE": "Component_Params",
                  "params": [
                    {
                      "value": {
                        "__OBJ_TYPE": "T_Part",
                        "action": "9e084268-1a31-411e-8a29-3f10ed194808"
                      }
                    }
                  ]
                }
              ],
              "id": {
                "value": "eeb5f9a4-9218-4ccd-b734-b3959c6b5340"
              },
              "pos": {
                "x": 1241.6598931275,
                "y": 414.51187782948
              }
            },
            {
              "__OBJ_TYPE": "Action_Test",
              "components": [
                {
                  "__OBJ_TYPE": "Component_Params",
                  "params": [
                    {
                      "value": {
                        "action": "f38b086f-a80d-4881-8db9-8ad3ff25824c"
                      }
                    }
                  ]
                }
              ],
              "id": {
                "value": "27c02f3e-500c-4e21-aa87-0580f4321b58"
              },
              "pos": {
                "x": 3044.3404731886,
                "y": 2013.5423505195
              }
            },
            {
              "__OBJ_TYPE": "Action_SetUserContextVar",
              "components": [
                {
                  "__OBJ_TYPE": "Component_Params",
                  "params": [
                    {
                      "value": {
                        "__OBJ_TYPE": "T_String",
                        "rawval": "time2"
                      }
                    },
                    {
                      "value": {
                        "__OBJ_TYPE": "T_Var",
                        "action": "b95bd9f6-4d11-4b1d-993d-455862d5057f"
                      }
                    }
                  ]
                }
              ],
              "id": {
                "value": "3546fd29-4186-47a7-9ae9-4a238c24db53"
              },
              "pos": {
                "x": 768.16061691331,
                "y": 236.51910814073
              }
            },
            {
              "__OBJ_TYPE": "Action_Test",
              "components": [
                {
                  "__OBJ_TYPE": "Component_Params",
                  "params": [
                    {
                      "value": {
                        "action": "a42c5f55-2a79-48ed-bff6-f4935b5002b0"
                      }
                    }
                  ]
                }
              ],
              "id": {
                "value": "4ce1e6d0-4e1d-411d-bc8d-bd3d207ee853"
              },
              "pos": {
                "x": 2521.8270958508,
                "y": 1634.9040027411
              }
            },
            {
              "__OBJ_TYPE": "Action_ComputeBool",
              "components": [
                {
                  "__OBJ_TYPE": "Component_Params",
                  "params": [
                    {
                      "value": {
                        "__OBJ_TYPE": "T_Double",
                        "action": "a3156adf-603a-4173-bf54-6783a760c439"
                      }
                    },
                    {
                      "value": {
                        "__OBJ_TYPE": "T_BinaryOperBool",
                        "rawval": "=="
                      }
                    },
                    {
                      "value": {
                        "__OBJ_TYPE": "T_Double"
                      }
                    }
                  ]
                }
              ],
              "id": {
                "value": "fac24308-792c-4720-a3d4-e28682badbb1"
              },
              "pos": {
                "x": 3030.1981046211,
                "y": 1806.3095097783
              }
            },
            {
              "__OBJ_TYPE": "Action_Test",
              "components": [
                {
                  "__OBJ_TYPE": "Component_Params",
                  "params": [
                    {
                      "value": {
                        "action": "45a4b20b-1dd4-477c-adb5-9af1ae3569a9"
                      }
                    }
                  ]
                }
              ],
              "id": {
                "value": "58b6654d-73fc-4bc1-af1b-b38440a9e95e"
              },
              "pos": {
                "x": 1342.0707099563,
                "y": 797.77006600669
              }
            },
            {
              "__OBJ_TYPE": "Action_GetUserContextVar",
              "components": [
                {
                  "__OBJ_TYPE": "Component_Params",
                  "params": [
                    {
                      "value": {
                        "__OBJ_TYPE": "T_String",
                        "rawval": "time2"
                      }
                    }
                  ]
                }
              ],
              "id": {
                "value": "a42c5f55-2a79-48ed-bff6-f4935b5002b0"
              },
              "pos": {
                "x": 2971.2715689236,
                "y": 1636.8839343406
              }
            },
            {
              "__OBJ_TYPE": "Action_GetUserContextVar",
              "components": [
                {
                  "__OBJ_TYPE": "Component_Params",
                  "params": [
                    {
                      "value": {
                        "__OBJ_TYPE": "T_String",
                        "rawval": "time2"
                      }
                    }
                  ]
                }
              ],
              "id": {
                "value": "a3156adf-603a-4173-bf54-6783a760c439"
              },
              "pos": {
                "x": 3467.7629880973,
                "y": 1806.3095097783
              }
            },
            {
              "__OBJ_TYPE": "Action_GetContextVar",
              "components": [
                {
                  "__OBJ_TYPE": "Component_Context",
                  "key": "part1"
                }
              ],
              "id": {
                "value": "9e084268-1a31-411e-8a29-3f10ed194808"
              },
              "pos": {
                "x": 1596.1619318843,
                "y": 318.343771571
              },
              "type": "T_Part"
            },
            {
              "__OBJ_TYPE": "Action_GetEntityMap",
              "components": [
                {
                  "__OBJ_TYPE": "Component_Params",
                  "params": [
                    {
                      "value": {
                        "__OBJ_TYPE": "T_Entity",
                        "action": "8c02bb2f-3ec3-4c07-a3e1-aa909fff09f1"
                      }
                    }
                  ]
                }
              ],
              "id": {
                "value": "54660abd-b75c-4431-adb8-7c8a3cf5aca5"
              },
              "pos": {
                "x": 3707.8323489177,
                "y": 2098.1969612032
              }
            },
            {
              "__OBJ_TYPE": "Action_NumberFloor",
              "components": [
                {
                  "__OBJ_TYPE": "Component_Params",
                  "params": [
                    {
                      "value": {
                        "__OBJ_TYPE": "T_Double",
                        "rawval": 1
                      }
                    }
                  ]
                }
              ],
              "id": {
                "value": "b95bd9f6-4d11-4b1d-993d-455862d5057f"
              },
              "pos": {
                "x": 1194.9800013083,
                "y": 244.49903974017
              }
            },
            {
              "__OBJ_TYPE": "Action_SetUserContextVar",
              "components": [
                {
                  "__OBJ_TYPE": "Component_Params",
                  "params": [
                    {
                      "value": {
                        "__OBJ_TYPE": "T_String",
                        "rawval": "place"
                      }
                    },
                    {
                      "value": {
                        "__OBJ_TYPE": "T_Var",
                        "action": "eeb5f9a4-9218-4ccd-b734-b3959c6b5340"
                      }
                    }
                  ]
                }
              ],
              "id": {
                "value": "8ff9b3e3-8675-4daf-8a83-4e35d52f3fc7"
              },
              "pos": {
                "x": 809.84623953553,
                "y": 408.85493040251
              }
            },
            {
              "__OBJ_TYPE": "Action_StartTimer2",
              "components": [
                {
                  "__OBJ_TYPE": "Component_Params",
                  "params": [
                    {
                      "value": {
                        "__OBJ_TYPE": "T_Time",
                        "rawval": {
                          "value": 20
                        }
                      }
                    },
                    {
                      "value": {
                        "__OBJ_TYPE": "T_Int",
                        "rawval": 1
                      }
                    },
                    {
                      "value": {
                        "__OBJ_TYPE": "T_String"
                      }
                    },
                    {
                      "value": {
                        "__OBJ_TYPE": "T_Entity"
                      }
                    }
                  ]
                },
                {
                  "__OBJ_TYPE": "Component_Sequence",
                  "children": [
                    {
                      "action": "125e552f-5a4a-4c11-b9e7-27b6dd9e6c57"
                    },
                    {
                      "action": "58b6654d-73fc-4bc1-af1b-b38440a9e95e"
                    },
                    {
                      "action": "e1846a5c-4bde-4b97-a875-be1b9d59c4d8"
                    }
                  ]
                }
              ],
              "id": {
                "value": "e0090bd0-4848-4c9f-850c-ffa986721c8e"
              },
              "pos": {
                "x": 800.73066118768,
                "y": 616.70593228473
              }
            },
            {
              "__OBJ_TYPE": "Action_If",
              "components": [
                {
                  "__OBJ_TYPE": "Component_Condition",
                  "children": [
                    {
                      "action": "dc6fcc66-a3a6-4ed2-b185-1e5d1f9dd94e"
                    }
                  ]
                }
              ],
              "id": {
                "value": "225e625f-2a65-4492-b5d8-96f060302767"
              },
              "pos": {
                "x": 2465.163339124,
                "y": 1788.1129955549
              }
            },
            {
              "__OBJ_TYPE": "Action_DestoryPart",
              "components": [
                {
                  "__OBJ_TYPE": "Component_Params",
                  "params": [
                    {
                      "value": {
                        "__OBJ_TYPE": "T_Part",
                        "action": "13df9016-0be0-4c07-9774-c8c6734fda28"
                      }
                    }
                  ]
                }
              ],
              "id": {
                "value": "f6cfde53-cb83-4294-9eb0-c27f86e3fd04"
              },
              "pos": {
                "x": 1907.9774800276,
                "y": 1203.1004602399
              }
            },
            {
              "__OBJ_TYPE": "Action_IfBranch",
              "components": [
                {
                  "__OBJ_TYPE": "Component_Params",
                  "params": [
                    {
                      "value": {
                        "__OBJ_TYPE": "T_Bool",
                        "action": "fac24308-792c-4720-a3d4-e28682badbb1"
                      }
                    }
                  ]
                },
                {
                  "__OBJ_TYPE": "Component_Sequence",
                  "children": [
                    {
                      "action": "27c02f3e-500c-4e21-aa87-0580f4321b58"
                    },
                    {
                      "action": "7648cf26-2c50-4196-9484-2ebd8e352789"
                    }
                  ]
                }
              ],
              "id": {
                "value": "dc6fcc66-a3a6-4ed2-b185-1e5d1f9dd94e"
              },
              "pos": {
                "x": 2708.6949258551,
                "y": 1865.330327933
              }
            },
            {
              "__OBJ_TYPE": "Action_SetUserContextVar",
              "components": [
                {
                  "__OBJ_TYPE": "Component_Params",
                  "params": [
                    {
                      "value": {
                        "__OBJ_TYPE": "T_String",
                        "rawval": "time1"
                      }
                    },
                    {
                      "value": {
                        "__OBJ_TYPE": "T_Var",
                        "action": "80997411-64db-41f4-a5f8-c305b5674a70"
                      }
                    }
                  ]
                }
              ],
              "id": {
                "value": "125e552f-5a4a-4c11-b9e7-27b6dd9e6c57"
              },
              "pos": {
                "x": 1325.2908663894,
                "y": 643.36305946119
              }
            },
            {
              "__OBJ_TYPE": "Action_GetUserContextVar",
              "components": [
                {
                  "__OBJ_TYPE": "Component_Params",
                  "params": [
                    {
                      "value": {
                        "__OBJ_TYPE": "T_String",
                        "rawval": "place"
                      }
                    }
                  ]
                }
              ],
              "id": {
                "value": "c6dfbb84-b54e-40b0-8911-01c1f7029dd2"
              },
              "pos": {
                "x": 3730.7167609942,
                "y": 2239.8202475983
              }
            },
            {
              "__OBJ_TYPE": "Action_SetUserContextVar",
              "components": [
                {
                  "__OBJ_TYPE": "Component_Params",
                  "params": [
                    {
                      "value": {
                        "__OBJ_TYPE": "T_String",
                        "rawval": "time1"
                      }
                    },
                    {
                      "value": {
                        "__OBJ_TYPE": "T_Var",
                        "action": "06938c04-ba70-4d86-babf-e01d1b6ce74f"
                      }
                    }
                  ]
                }
              ],
              "id": {
                "value": "0aa50098-957a-4a2f-8038-11d64038fe41"
              },
              "pos": {
                "x": 745.16061691331,
                "y": 88.579313342412
              }
            },
            {
              "__OBJ_TYPE": "Action_StartTimer2",
              "components": [
                {
                  "__OBJ_TYPE": "Component_Params",
                  "params": [
                    {
                      "value": {
                        "__OBJ_TYPE": "T_Time",
                        "rawval": {
                          "value": 20
                        }
                      }
                    },
                    {
                      "value": {
                        "__OBJ_TYPE": "T_Int",
                        "rawval": 1
                      }
                    },
                    {
                      "value": {
                        "__OBJ_TYPE": "T_String"
                      }
                    },
                    {
                      "value": {
                        "__OBJ_TYPE": "T_Entity"
                      }
                    }
                  ]
                },
                {
                  "__OBJ_TYPE": "Component_Sequence",
                  "children": [
                    {
                      "action": "fe5c4e57-a28e-45fd-bde9-a97f6c58c98f"
                    },
                    {
                      "action": "4ce1e6d0-4e1d-411d-bc8d-bd3d207ee853"
                    },
                    {
                      "action": "225e625f-2a65-4492-b5d8-96f060302767"
                    }
                  ]
                }
              ],
              "id": {
                "value": "ce0b3d48-3207-4b07-9fb3-405abd5497a9"
              },
              "pos": {
                "x": 1874.5393952433,
                "y": 1365.5654534808
              }
            },
            {
              "__OBJ_TYPE": "Action_ComputeInt",
              "components": [
                {
                  "__OBJ_TYPE": "Component_Params",
                  "params": [
                    {
                      "value": {
                        "__OBJ_TYPE": "T_Int",
                        "action": "6c1d3e17-1c0b-499f-b14a-df234d1a4e09"
                      }
                    },
                    {
                      "value": {
                        "__OBJ_TYPE": "T_BinaryOperCompute",
                        "rawval": "-"
                      }
                    },
                    {
                      "value": {
                        "__OBJ_TYPE": "T_Int",
                        "rawval": 1
                      }
                    }
                  ]
                }
              ],
              "id": {
                "value": "80997411-64db-41f4-a5f8-c305b5674a70"
              },
              "pos": {
                "x": 1749.2908663894,
                "y": 491.36305946118
              }
            },
            {
              "__OBJ_TYPE": "Action_GetUserContextVar",
              "components": [
                {
                  "__OBJ_TYPE": "Component_Params",
                  "params": [
                    {
                      "value": {
                        "__OBJ_TYPE": "T_String",
                        "rawval": "place"
                      }
                    }
                  ]
                }
              ],
              "id": {
                "value": "f38b086f-a80d-4881-8db9-8ad3ff25824c"
              },
              "pos": {
                "x": 3427.1272490802,
                "y": 1983.3719642424
              }
            },
            {
              "__OBJ_TYPE": "Action_GetContextVar",
              "components": [
                {
                  "__OBJ_TYPE": "Component_Context",
                  "key": "part1"
                }
              ],
              "id": {
                "value": "13df9016-0be0-4c07-9774-c8c6734fda28"
              },
              "pos": {
                "x": 2256.9373432265,
                "y": 1189.2208706432
              },
              "type": "T_Part"
            },
            {
              "__OBJ_TYPE": "Action_CreatePartByPartStorage",
              "components": [
                {
                  "__OBJ_TYPE": "Component_Params",
                  "params": [
                    {
                      "value": {
                        "__OBJ_TYPE": "T_StorageEntry",
                        "rawval": {
                          "id": "8673307749779734529",
                          "name": "Broken plate"
                        }
                      }
                    },
                    {
                      "value": {
                        "__OBJ_TYPE": "T_Map",
                        "action": "54660abd-b75c-4431-adb8-7c8a3cf5aca5"
                      }
                    },
                    {
                      "value": {
                        "__OBJ_TYPE": "T_ScenePos",
                        "action": "c6dfbb84-b54e-40b0-8911-01c1f7029dd2"
                      }
                    }
                  ]
                }
              ],
              "id": {
                "value": "7648cf26-2c50-4196-9484-2ebd8e352789"
              },
              "pos": {
                "x": 3036.8323489177,
                "y": 2178.7933131733
              }
            },
            {
              "__OBJ_TYPE": "Action_IfBranch",
              "components": [
                {
                  "__OBJ_TYPE": "Component_Params",
                  "params": [
                    {
                      "value": {
                        "__OBJ_TYPE": "T_Bool",
                        "action": "afeef0fe-f969-4ad7-b754-44ba173b6211"
                      }
                    }
                  ]
                },
                {
                  "__OBJ_TYPE": "Component_Sequence",
                  "children": [
                    {
                      "action": "f6cfde53-cb83-4294-9eb0-c27f86e3fd04"
                    },
                    {
                      "action": "ce0b3d48-3207-4b07-9fb3-405abd5497a9"
                    }
                  ]
                }
              ],
              "id": {
                "value": "bdceb364-a30d-47af-b1d1-0e4faf28aa8f"
              },
              "pos": {
                "x": 1543.4774800276,
                "y": 1182.6004602399
              }
            },
            {
              "__OBJ_TYPE": "Action_ComputeBool",
              "components": [
                {
                  "__OBJ_TYPE": "Component_Params",
                  "params": [
                    {
                      "value": {
                        "__OBJ_TYPE": "T_Double",
                        "action": "17397c64-b186-499c-a5e3-aa46e2609bed"
                      }
                    },
                    {
                      "value": {
                        "__OBJ_TYPE": "T_BinaryOperBool",
                        "rawval": "=="
                      }
                    },
                    {
                      "value": {
                        "__OBJ_TYPE": "T_Double"
                      }
                    }
                  ]
                }
              ],
              "id": {
                "value": "afeef0fe-f969-4ad7-b754-44ba173b6211"
              },
              "pos": {
                "x": 1765.9954789152,
                "y": 959.20137224736
              }
            },
            {
              "__OBJ_TYPE": "Action_SetUserContextVar",
              "components": [
                {
                  "__OBJ_TYPE": "Component_Params",
                  "params": [
                    {
                      "value": {
                        "__OBJ_TYPE": "T_String",
                        "rawval": "time2"
                      }
                    },
                    {
                      "value": {
                        "__OBJ_TYPE": "T_Var",
                        "action": "50c7eef9-7a89-4072-8d72-5149879e138f"
                      }
                    }
                  ]
                }
              ],
              "id": {
                "value": "fe5c4e57-a28e-45fd-bde9-a97f6c58c98f"
              },
              "pos": {
                "x": 2389.1345101477,
                "y": 1477.2720740072
              }
            },
            {
              "__OBJ_TYPE": "Action_ComputeInt",
              "components": [
                {
                  "__OBJ_TYPE": "Component_Params",
                  "params": [
                    {
                      "value": {
                        "__OBJ_TYPE": "T_Int",
                        "action": "0af25e2e-433b-4507-8d4d-c6df118037c9"
                      }
                    },
                    {
                      "value": {
                        "__OBJ_TYPE": "T_BinaryOperCompute",
                        "rawval": "-"
                      }
                    },
                    {
                      "value": {
                        "__OBJ_TYPE": "T_Int",
                        "rawval": 1
                      }
                    }
                  ]
                }
              ],
              "id": {
                "value": "50c7eef9-7a89-4072-8d72-5149879e138f"
              },
              "pos": {
                "x": 2813.1345101477,
                "y": 1325.2720740072
              }
            },
            {
              "__OBJ_TYPE": "Action_GetUserContextVar",
              "components": [
                {
                  "__OBJ_TYPE": "Component_Params",
                  "params": [
                    {
                      "value": {
                        "__OBJ_TYPE": "T_String",
                        "rawval": "time1"
                      }
                    }
                  ]
                }
              ],
              "id": {
                "value": "45a4b20b-1dd4-477c-adb5-9af1ae3569a9"
              },
              "pos": {
                "x": 1700.4383294548,
                "y": 803.70986080501
              }
            },
            {
              "__OBJ_TYPE": "Action_NumberFloor",
              "components": [
                {
                  "__OBJ_TYPE": "Component_Params",
                  "params": [
                    {
                      "value": {
                        "__OBJ_TYPE": "T_Double",
                        "rawval": 1
                      }
                    }
                  ]
                }
              ],
              "id": {
                "value": "06938c04-ba70-4d86-babf-e01d1b6ce74f"
              },
              "pos": {
                "x": 1151.1606169133,
                "y": 102.57931334241
              }
            },
            {
              "__OBJ_TYPE": "Action_GetUserContextVar",
              "components": [
                {
                  "__OBJ_TYPE": "Component_Params",
                  "params": [
                    {
                      "value": {
                        "__OBJ_TYPE": "T_String",
                        "rawval": "time2"
                      }
                    }
                  ]
                }
              ],
              "id": {
                "value": "0af25e2e-433b-4507-8d4d-c6df118037c9"
              },
              "pos": {
                "x": 3248.4991613858,
                "y": 1326.1751520325
              }
            },
            {
              "__OBJ_TYPE": "Action_GetUserContextVar",
              "components": [
                {
                  "__OBJ_TYPE": "Component_Params",
                  "params": [
                    {
                      "value": {
                        "__OBJ_TYPE": "T_String",
                        "rawval": "time1"
                      }
                    }
                  ]
                }
              ],
              "id": {
                "value": "17397c64-b186-499c-a5e3-aa46e2609bed"
              },
              "pos": {
                "x": 2180.9954789152,
                "y": 967.2816458496
              }
            },
            {
              "__OBJ_TYPE": "Action_GetUserContextVar",
              "components": [
                {
                  "__OBJ_TYPE": "Component_Params",
                  "params": [
                    {
                      "value": {
                        "__OBJ_TYPE": "T_String",
                        "rawval": "time1"
                      }
                    }
                  ]
                }
              ],
              "id": {
                "value": "6c1d3e17-1c0b-499f-b14a-df234d1a4e09"
              },
              "pos": {
                "x": 2319.2908663894,
                "y": 581.36305946118
              }
            },
            {
              "__OBJ_TYPE": "Action_If",
              "components": [
                {
                  "__OBJ_TYPE": "Component_Condition",
                  "children": [
                    {
                      "action": "bdceb364-a30d-47af-b1d1-0e4faf28aa8f"
                    }
                  ]
                }
              ],
              "id": {
                "value": "e1846a5c-4bde-4b97-a875-be1b9d59c4d8"
              },
              "pos": {
                "x": 1305.4373432265,
                "y": 1164.7610074444
              }
            },
            {
              "__OBJ_TYPE": "Action_GetContextVar",
              "components": [
                {
                  "__OBJ_TYPE": "Component_Context",
                  "key": "obj2"
                }
              ],
              "id": {
                "value": "8c02bb2f-3ec3-4c07-a3e1-aa909fff09f1"
              },
              "pos": {
                "x": 4089.8323489177,
                "y": 2077.1969612032
              },
              "type": "T_Entity"
            }
          ],
          "custom_trigger_data": {
            "name": {
              "value": "e863dc3a-bbd6-45aa-b593-fca62f99789f"
            }
          },
          "root": {
            "components": [
              {
                "__OBJ_TYPE": "Component_Sequence",
                "children": [
                  {
                    "action": "0aa50098-957a-4a2f-8038-11d64038fe41"
                  },
                  {
                    "action": "3546fd29-4186-47a7-9ae9-4a238c24db53"
                  },
                  {
                    "action": "8ff9b3e3-8675-4daf-8a83-4e35d52f3fc7"
                  },
                  {
                    "action": "e0090bd0-4848-4c9f-850c-ffa986721c8e"
                  }
                ]
              }
            ],
            "id": {
              "value": "d3298ed2-6b70-4174-8602-aadd354d9601"
            },
            "pos": {
              "x": 253,
              "y": 264
            }
          },
          "type": "Trigger_PartTouchEntityBegin"
        }
      ]
    }
  },
  "meta": {
    "EXPORT": {
      "triggers.bts": "71c9138271db25231fd615d50d28cbdf"
    },
    "VERSION": "0.21"
  }
}